textspread/__init__.py
textspread/main.py
textspread-2.0.1.dist-info/LICENSE
textspread-2.0.1.dist-info/METADATA
textspread-2.0.1.dist-info/WHEEL
textspread-2.0.1.dist-info/entry_points.txt
textspread-2.0.1.dist-info/top_level.txt
textspread-2.0.1.dist-info/RECORD
