Metadata-Version: 2.1
Name: textspread
Version: 2.0.1
Summary: Textspread takes in a .txt file and appends its contents into a spreadsheet
Author-email: t0mri <dat0mri@proton.me>
License: GNU GENERAL PUBLIC LICENSE
Project-URL: Homepage, https://github.com/t0mri/textspread
Project-URL: Documentation, https://github.com/t0mri/textspread/README.md
Project-URL: Repository, https://github.com/t0mri/textspread
Project-URL: Issues, https://github.com/t0mri/textspread/issues
Keywords: text to excel,text to xl,text to spreadsheet,txt to excel,txt to xl,txt to spreadsheet
Classifier: Programming Language :: Python :: 3
Classifier: License :: OSI Approved :: GNU General Public License v3 (GPLv3)
Classifier: Operating System :: OS Independent
Requires-Python: >=3.8
License-File: LICENSE
Requires-Dist: openpyxl
